tactus_model/__init__.py
tactus_model/hyperparam_tuning.py
tactus_model/model_eval.py
tactus_model/utils/__init__.py
tactus_model/utils/classifier.py
tactus_model/utils/torch_mlp.py
tactus_model/utils/tracker.py
tactus_model-1.1.0.dist-info/METADATA
tactus_model-1.1.0.dist-info/WHEEL
tactus_model-1.1.0.dist-info/top_level.txt
tactus_model-1.1.0.dist-info/RECORD
