Metadata-Version: 2.1
Name: tactus-model
Version: 1.1.0
Summary: Threatening activities classification toward users' security
Project-URL: repository, https://github.com/Cranfield-GDP3/TACTUS-model
Classifier: Development Status :: 5 - Production/Stable
Classifier: Intended Audience :: Developers
Classifier: Programming Language :: Python
Requires-Python: >=3.8
Requires-Dist: numpy
Requires-Dist: scikit-learn
Requires-Dist: tactus-data
Requires-Dist: pytest
